{
  "name": "me",
  "handedness": "right",
  "note": "Ideal learned from 10 your best-ranked shots. Ideal skeletons from 2 clean-pose shots (load, release, follow).",
  "n_good": 10,
  "source_method": "your best-ranked shots",
  "ideal": {
    "elbow_angle_at_release_deg": 118.9,
    "knee_bend_deg": 113.03,
    "tempo_dip_to_release_s": 0.12,
    "follow_through_hold_s": 0.03,
    "balance_drift_px_per_ht": 2.67,
    "release_angle_deg": 53.6,
    "entry_angle_deg": 43.5
  },
  "tolerance": {
    "elbow_angle_at_release_deg": 55.3,
    "knee_bend_deg": 36.55,
    "tempo_dip_to_release_s": 0.11,
    "follow_through_hold_s": 0.1,
    "balance_drift_px_per_ht": 1.93,
    "release_angle_deg": 14.57,
    "entry_angle_deg": 9.52
  },
  "skeletons": {
    "load": [
      {
        "x": 0.5055,
        "y": 0.3808,
        "visibility": 0.997
      },
      {
        "x": 0.509,
        "y": 0.3666,
        "visibility": 0.996
      },
      {
        "x": 0.5101,
        "y": 0.3655,
        "visibility": 0.997
      },
      {
        "x": 0.5112,
        "y": 0.3641,
        "visibility": 0.997
      },
      {
        "x": 0.5056,
        "y": 0.3692,
        "visibility": 0.995
      },
      {
        "x": 0.5048,
        "y": 0.3681,
        "visibility": 0.995
      },
      {
        "x": 0.5047,
        "y": 0.3689,
        "visibility": 0.994
      },
      {
        "x": 0.514,
        "y": 0.3635,
        "visibility": 0.995
      },
      {
        "x": 0.5023,
        "y": 0.3701,
        "visibility": 0.987
      },
      {
        "x": 0.5066,
        "y": 0.3883,
        "visibility": 0.994
      },
      {
        "x": 0.5021,
        "y": 0.3897,
        "visibility": 0.991
      },
      {
        "x": 0.5151,
        "y": 0.4134,
        "visibility": 1.0
      },
      {
        "x": 0.4849,
        "y": 0.4266,
        "visibility": 0.999
      },
      {
        "x": 0.5091,
        "y": 0.5115,
        "visibility": 0.825
      },
      {
        "x": 0.4866,
        "y": 0.4583,
        "visibility": 0.778
      },
      {
        "x": 0.4963,
        "y": 0.5738,
        "visibility": 0.738
      },
      {
        "x": 0.4869,
        "y": 0.4881,
        "visibility": 0.814
      },
      {
        "x": 0.4943,
        "y": 0.5951,
        "visibility": 0.69
      },
      {
        "x": 0.4856,
        "y": 0.5025,
        "visibility": 0.775
      },
      {
        "x": 0.4927,
        "y": 0.5893,
        "visibility": 0.691
      },
      {
        "x": 0.4871,
        "y": 0.5008,
        "visibility": 0.779
      },
      {
        "x": 0.4948,
        "y": 0.583,
        "visibility": 0.677
      },
      {
        "x": 0.4893,
        "y": 0.4978,
        "visibility": 0.766
      },
      {
        "x": 0.5138,
        "y": 0.5916,
        "visibility": 0.997
      },
      {
        "x": 0.4899,
        "y": 0.6069,
        "visibility": 0.998
      },
      {
        "x": 0.526,
        "y": 0.7232,
        "visibility": 0.884
      },
      {
        "x": 0.4811,
        "y": 0.7723,
        "visibility": 0.827
      },
      {
        "x": 0.5244,
        "y": 0.8855,
        "visibility": 0.893
      },
      {
        "x": 0.4817,
        "y": 0.8889,
        "visibility": 0.848
      },
      {
        "x": 0.5225,
        "y": 0.9099,
        "visibility": 0.844
      },
      {
        "x": 0.4816,
        "y": 0.8968,
        "visibility": 0.836
      },
      {
        "x": 0.5204,
        "y": 0.9268,
        "visibility": 0.893
      },
      {
        "x": 0.4809,
        "y": 0.9563,
        "visibility": 0.851
      }
    ],
    "release": [
      {
        "x": 0.4987,
        "y": 0.3664,
        "visibility": 0.998
      },
      {
        "x": 0.4993,
        "y": 0.3585,
        "visibility": 0.998
      },
      {
        "x": 0.4985,
        "y": 0.3588,
        "visibility": 0.999
      },
      {
        "x": 0.4976,
        "y": 0.359,
        "visibility": 0.998
      },
      {
        "x": 0.5025,
        "y": 0.3582,
        "visibility": 0.998
      },
      {
        "x": 0.504,
        "y": 0.3584,
        "visibility": 0.998
      },
      {
        "x": 0.5054,
        "y": 0.3584,
        "visibility": 0.997
      },
      {
        "x": 0.4977,
        "y": 0.3651,
        "visibility": 0.998
      },
      {
        "x": 0.5077,
        "y": 0.3654,
        "visibility": 0.997
      },
      {
        "x": 0.4979,
        "y": 0.3749,
        "visibility": 0.996
      },
      {
        "x": 0.5012,
        "y": 0.3752,
        "visibility": 0.994
      },
      {
        "x": 0.4816,
        "y": 0.4275,
        "visibility": 0.999
      },
      {
        "x": 0.5183,
        "y": 0.4125,
        "visibility": 0.998
      },
      {
        "x": 0.4575,
        "y": 0.5458,
        "visibility": 0.858
      },
      {
        "x": 0.5356,
        "y": 0.3592,
        "visibility": 0.874
      },
      {
        "x": 0.4479,
        "y": 0.6306,
        "visibility": 0.703
      },
      {
        "x": 0.5215,
        "y": 0.2403,
        "visibility": 0.774
      },
      {
        "x": 0.4464,
        "y": 0.6561,
        "visibility": 0.585
      },
      {
        "x": 0.5234,
        "y": 0.2137,
        "visibility": 0.69
      },
      {
        "x": 0.4502,
        "y": 0.6594,
        "visibility": 0.592
      },
      {
        "x": 0.5191,
        "y": 0.2156,
        "visibility": 0.687
      },
      {
        "x": 0.4511,
        "y": 0.6509,
        "visibility": 0.566
      },
      {
        "x": 0.5154,
        "y": 0.2206,
        "visibility": 0.662
      },
      {
        "x": 0.4986,
        "y": 0.6042,
        "visibility": 1.0
      },
      {
        "x": 0.5133,
        "y": 0.5956,
        "visibility": 0.999
      },
      {
        "x": 0.4873,
        "y": 0.7092,
        "visibility": 0.849
      },
      {
        "x": 0.4916,
        "y": 0.7167,
        "visibility": 0.796
      },
      {
        "x": 0.4711,
        "y": 0.8361,
        "visibility": 0.909
      },
      {
        "x": 0.5092,
        "y": 0.857,
        "visibility": 0.895
      },
      {
        "x": 0.4721,
        "y": 0.8485,
        "visibility": 0.904
      },
      {
        "x": 0.5127,
        "y": 0.8759,
        "visibility": 0.906
      },
      {
        "x": 0.4536,
        "y": 0.873,
        "visibility": 0.868
      },
      {
        "x": 0.4967,
        "y": 0.909,
        "visibility": 0.82
      }
    ],
    "follow": [
      {
        "x": 0.5033,
        "y": 0.3763,
        "visibility": 0.999
      },
      {
        "x": 0.5068,
        "y": 0.3646,
        "visibility": 0.999
      },
      {
        "x": 0.5078,
        "y": 0.3642,
        "visibility": 0.998
      },
      {
        "x": 0.5089,
        "y": 0.3637,
        "visibility": 0.999
      },
      {
        "x": 0.5049,
        "y": 0.3646,
        "visibility": 0.999
      },
      {
        "x": 0.5044,
        "y": 0.3641,
        "visibility": 0.999
      },
      {
        "x": 0.5037,
        "y": 0.3636,
        "visibility": 0.999
      },
      {
        "x": 0.5112,
        "y": 0.3651,
        "visibility": 0.997
      },
      {
        "x": 0.5026,
        "y": 0.364,
        "visibility": 0.998
      },
      {
        "x": 0.5039,
        "y": 0.3873,
        "visibility": 0.998
      },
      {
        "x": 0.5011,
        "y": 0.3869,
        "visibility": 0.999
      },
      {
        "x": 0.5194,
        "y": 0.4178,
        "visibility": 0.999
      },
      {
        "x": 0.4806,
        "y": 0.4222,
        "visibility": 1.0
      },
      {
        "x": 0.5308,
        "y": 0.4629,
        "visibility": 0.641
      },
      {
        "x": 0.4551,
        "y": 0.4901,
        "visibility": 0.942
      },
      {
        "x": 0.5067,
        "y": 0.4502,
        "visibility": 0.704
      },
      {
        "x": 0.4575,
        "y": 0.5339,
        "visibility": 0.957
      },
      {
        "x": 0.4989,
        "y": 0.4503,
        "visibility": 0.699
      },
      {
        "x": 0.4558,
        "y": 0.5486,
        "visibility": 0.929
      },
      {
        "x": 0.499,
        "y": 0.446,
        "visibility": 0.703
      },
      {
        "x": 0.4594,
        "y": 0.5444,
        "visibility": 0.928
      },
      {
        "x": 0.5005,
        "y": 0.4468,
        "visibility": 0.686
      },
      {
        "x": 0.4604,
        "y": 0.5401,
        "visibility": 0.912
      },
      {
        "x": 0.5092,
        "y": 0.5977,
        "visibility": 0.999
      },
      {
        "x": 0.4818,
        "y": 0.6007,
        "visibility": 0.999
      },
      {
        "x": 0.5186,
        "y": 0.7277,
        "visibility": 0.92
      },
      {
        "x": 0.4845,
        "y": 0.7374,
        "visibility": 0.975
      },
      {
        "x": 0.5098,
        "y": 0.8294,
        "visibility": 0.956
      },
      {
        "x": 0.4657,
        "y": 0.8289,
        "visibility": 0.979
      },
      {
        "x": 0.5067,
        "y": 0.8393,
        "visibility": 0.911
      },
      {
        "x": 0.4659,
        "y": 0.8429,
        "visibility": 0.943
      },
      {
        "x": 0.5063,
        "y": 0.8714,
        "visibility": 0.962
      },
      {
        "x": 0.4635,
        "y": 0.8665,
        "visibility": 0.978
      }
    ]
  }
}